<?xml version="1.0" encoding="UTF-8"?><record_update>
    <sys_choice action="INSERT_OR_UPDATE" field="accounttype" table="x_437100_arc_cmdb_appconfig_account_types" version="3">
        <sys_choice_set action="INSERT_OR_UPDATE">
            <element>accounttype</element>
            <name>x_437100_arc_cmdb_appconfig_account_types</name>
            <sys_class_name>sys_choice_set</sys_class_name>
            <sys_created_by>admin</sys_created_by>
            <sys_created_on>2020-07-20 13:03:23</sys_created_on>
            <sys_id>d7ac117edbc21010b0235c7a489619c7</sys_id>
            <sys_mod_count>0</sys_mod_count>
            <sys_name>accounttype</sys_name>
            <sys_package display_value="ARC-CMDB" source="x_437100_arc_cmdb">360d4b9edb220010b0235c7a4896197b</sys_package>
            <sys_policy/>
            <sys_scope display_value="ARC-CMDB">360d4b9edb220010b0235c7a4896197b</sys_scope>
            <sys_update_name>sys_choice_x_437100_arc_cmdb_appconfig_account_types_accounttype</sys_update_name>
            <sys_updated_by>admin</sys_updated_by>
            <sys_updated_on>2020-07-20 13:03:23</sys_updated_on>
        </sys_choice_set>
        <sys_choice action="INSERT_OR_UPDATE">
            <dependent_value/>
            <element>accounttype</element>
            <hint/>
            <inactive>false</inactive>
            <label>Elevated Account</label>
            <language>en</language>
            <name>x_437100_arc_cmdb_appconfig_account_types</name>
            <sequence>1</sequence>
            <sys_created_by>admin</sys_created_by>
            <sys_created_on>2020-07-20 13:03:23</sys_created_on>
            <sys_domain>global</sys_domain>
            <sys_domain_path>/</sys_domain_path>
            <sys_id>4b6a557edbc21010b0235c7a48961940</sys_id>
            <sys_mod_count>2</sys_mod_count>
            <sys_updated_by>admin</sys_updated_by>
            <sys_updated_on>2020-07-20 13:03:32</sys_updated_on>
            <value>elevated account</value>
        </sys_choice>
        <sys_choice action="INSERT_OR_UPDATE">
            <dependent_value/>
            <element>accounttype</element>
            <hint/>
            <inactive>false</inactive>
            <label>Server Based Account</label>
            <language>en</language>
            <name>x_437100_arc_cmdb_appconfig_account_types</name>
            <sequence>2</sequence>
            <sys_created_by>admin</sys_created_by>
            <sys_created_on>2020-07-20 13:03:41</sys_created_on>
            <sys_domain>global</sys_domain>
            <sys_domain_path>/</sys_domain_path>
            <sys_id>9fac91bedbc21010b0235c7a4896190c</sys_id>
            <sys_mod_count>2</sys_mod_count>
            <sys_updated_by>admin</sys_updated_by>
            <sys_updated_on>2020-07-20 13:03:50</sys_updated_on>
            <value>server based account</value>
        </sys_choice>
        <sys_choice action="INSERT_OR_UPDATE">
            <dependent_value/>
            <element>accounttype</element>
            <hint/>
            <inactive>false</inactive>
            <label>Service Account</label>
            <language>en</language>
            <name>x_437100_arc_cmdb_appconfig_account_types</name>
            <sequence>3</sequence>
            <sys_created_by>admin</sys_created_by>
            <sys_created_on>2020-07-20 13:03:56</sys_created_on>
            <sys_domain>global</sys_domain>
            <sys_domain_path>/</sys_domain_path>
            <sys_id>7bbcd57edbc21010b0235c7a48961962</sys_id>
            <sys_mod_count>2</sys_mod_count>
            <sys_updated_by>admin</sys_updated_by>
            <sys_updated_on>2020-07-20 13:04:05</sys_updated_on>
            <value>service account</value>
        </sys_choice>
        <sys_choice action="INSERT_OR_UPDATE">
            <dependent_value/>
            <element>accounttype</element>
            <hint/>
            <inactive>false</inactive>
            <label>AD Account</label>
            <language>en</language>
            <name>x_437100_arc_cmdb_appconfig_account_types</name>
            <sequence>4</sequence>
            <sys_created_by>admin</sys_created_by>
            <sys_created_on>2020-07-20 13:04:12</sys_created_on>
            <sys_domain>global</sys_domain>
            <sys_domain_path>/</sys_domain_path>
            <sys_id>23cc117edbc21010b0235c7a48961948</sys_id>
            <sys_mod_count>2</sys_mod_count>
            <sys_updated_by>admin</sys_updated_by>
            <sys_updated_on>2020-07-20 13:04:19</sys_updated_on>
            <value>ad account</value>
        </sys_choice>
        <sys_choice action="INSERT_OR_UPDATE">
            <dependent_value/>
            <element>accounttype</element>
            <hint/>
            <inactive>false</inactive>
            <label>Account Type TBD</label>
            <language>en</language>
            <name>x_437100_arc_cmdb_appconfig_account_types</name>
            <sequence>5</sequence>
            <sys_created_by>admin</sys_created_by>
            <sys_created_on>2020-07-20 13:04:27</sys_created_on>
            <sys_domain>global</sys_domain>
            <sys_domain_path>/</sys_domain_path>
            <sys_id>53dc9dbedbc21010b0235c7a489619e9</sys_id>
            <sys_mod_count>2</sys_mod_count>
            <sys_updated_by>admin</sys_updated_by>
            <sys_updated_on>2020-07-20 13:04:43</sys_updated_on>
            <value>account type tbd</value>
        </sys_choice>
        <sys_choice action="INSERT_OR_UPDATE">
            <dependent_value/>
            <element>accounttype</element>
            <hint/>
            <inactive>false</inactive>
            <label>App-Side Account</label>
            <language>en</language>
            <name>x_437100_arc_cmdb_appconfig_account_types</name>
            <sequence>6</sequence>
            <sys_created_by>admin</sys_created_by>
            <sys_created_on>2020-07-20 13:04:49</sys_created_on>
            <sys_domain>global</sys_domain>
            <sys_domain_path>/</sys_domain_path>
            <sys_id>0becddbedbc21010b0235c7a489619f0</sys_id>
            <sys_mod_count>2</sys_mod_count>
            <sys_updated_by>admin</sys_updated_by>
            <sys_updated_on>2020-07-20 13:04:59</sys_updated_on>
            <value>app-side account</value>
        </sys_choice>
        <sys_choice action="INSERT_OR_UPDATE">
            <dependent_value/>
            <element>accounttype</element>
            <hint/>
            <inactive>false</inactive>
            <label>N\A</label>
            <language>en</language>
            <name>x_437100_arc_cmdb_appconfig_account_types</name>
            <sequence>7</sequence>
            <sys_created_by>admin</sys_created_by>
            <sys_created_on>2020-07-20 13:05:07</sys_created_on>
            <sys_domain>global</sys_domain>
            <sys_domain_path>/</sys_domain_path>
            <sys_id>6c0d51fedbc21010b0235c7a4896197a</sys_id>
            <sys_mod_count>2</sys_mod_count>
            <sys_updated_by>admin</sys_updated_by>
            <sys_updated_on>2020-07-20 13:05:14</sys_updated_on>
            <value>n\a</value>
        </sys_choice>
        <sys_choice action="INSERT_OR_UPDATE">
            <dependent_value/>
            <element>accounttype</element>
            <hint/>
            <inactive>false</inactive>
            <label>1. Not Provided in Application Registry (AR)</label>
            <language>en</language>
            <name>x_437100_arc_cmdb_appconfig_account_types</name>
            <sequence>8</sequence>
            <sys_created_by>admin</sys_created_by>
            <sys_created_on>2020-07-20 13:05:27</sys_created_on>
            <sys_domain>global</sys_domain>
            <sys_domain_path>/</sys_domain_path>
            <sys_id>bc1d51fedbc21010b0235c7a4896190b</sys_id>
            <sys_mod_count>2</sys_mod_count>
            <sys_updated_by>admin</sys_updated_by>
            <sys_updated_on>2020-07-20 13:05:31</sys_updated_on>
            <value>1. Not Provided in Application Registry (AR)</value>
        </sys_choice>
        <sys_choice action="INSERT_OR_UPDATE">
            <dependent_value/>
            <element>accounttype</element>
            <hint/>
            <inactive>false</inactive>
            <label>2. Not Provided in Team Foundation Server (TFS)</label>
            <language>en</language>
            <name>x_437100_arc_cmdb_appconfig_account_types</name>
            <sequence>9</sequence>
            <sys_created_by>admin</sys_created_by>
            <sys_created_on>2020-07-20 13:05:45</sys_created_on>
            <sys_domain>global</sys_domain>
            <sys_domain_path>/</sys_domain_path>
            <sys_id>ad2d51fedbc21010b0235c7a48961970</sys_id>
            <sys_mod_count>2</sys_mod_count>
            <sys_updated_by>admin</sys_updated_by>
            <sys_updated_on>2020-07-20 13:05:50</sys_updated_on>
            <value>2. Not Provided in Team Foundation Server (TFS)</value>
        </sys_choice>
        <sys_choice action="INSERT_OR_UPDATE">
            <dependent_value/>
            <element>accounttype</element>
            <hint/>
            <inactive>false</inactive>
            <label>3. Not Found During Code Review (CR)</label>
            <language>en</language>
            <name>x_437100_arc_cmdb_appconfig_account_types</name>
            <sequence>10</sequence>
            <sys_created_by>admin</sys_created_by>
            <sys_created_on>2020-07-20 13:06:01</sys_created_on>
            <sys_domain>global</sys_domain>
            <sys_domain_path>/</sys_domain_path>
            <sys_id>863d51fedbc21010b0235c7a48961913</sys_id>
            <sys_mod_count>2</sys_mod_count>
            <sys_updated_by>admin</sys_updated_by>
            <sys_updated_on>2020-07-20 13:06:05</sys_updated_on>
            <value>3. Not Found During Code Review (CR)</value>
        </sys_choice>
        <sys_choice action="INSERT_OR_UPDATE">
            <dependent_value/>
            <element>accounttype</element>
            <hint/>
            <inactive>false</inactive>
            <label>4. Not Provided in COTS Documentation (COTSD)</label>
            <language>en</language>
            <name>x_437100_arc_cmdb_appconfig_account_types</name>
            <sequence>11</sequence>
            <sys_created_by>admin</sys_created_by>
            <sys_created_on>2020-07-20 13:06:15</sys_created_on>
            <sys_domain>global</sys_domain>
            <sys_domain_path>/</sys_domain_path>
            <sys_id>ce4dd1fedbc21010b0235c7a48961949</sys_id>
            <sys_mod_count>2</sys_mod_count>
            <sys_updated_by>admin</sys_updated_by>
            <sys_updated_on>2020-07-20 13:06:19</sys_updated_on>
            <value>4. Not Provided in COTS Documentation (COTSD)</value>
        </sys_choice>
        <sys_choice action="INSERT_OR_UPDATE">
            <dependent_value/>
            <element>accounttype</element>
            <hint/>
            <inactive>false</inactive>
            <label>5. Not Provided during SME Interview (SMEI)</label>
            <language>en</language>
            <name>x_437100_arc_cmdb_appconfig_account_types</name>
            <sequence>12</sequence>
            <sys_created_by>admin</sys_created_by>
            <sys_created_on>2020-07-20 13:06:29</sys_created_on>
            <sys_domain>global</sys_domain>
            <sys_domain_path>/</sys_domain_path>
            <sys_id>5d5d5dbedbc21010b0235c7a48961908</sys_id>
            <sys_mod_count>2</sys_mod_count>
            <sys_updated_by>admin</sys_updated_by>
            <sys_updated_on>2020-07-20 13:06:33</sys_updated_on>
            <value>5. Not Provided during SME Interview (SMEI)</value>
        </sys_choice>
        <sys_choice action="INSERT_OR_UPDATE">
            <dependent_value/>
            <element>accounttype</element>
            <hint/>
            <inactive>false</inactive>
            <label>6. Not Provided by any Authoritative Source</label>
            <language>en</language>
            <name>x_437100_arc_cmdb_appconfig_account_types</name>
            <sequence>13</sequence>
            <sys_created_by>admin</sys_created_by>
            <sys_created_on>2020-07-20 13:06:45</sys_created_on>
            <sys_domain>global</sys_domain>
            <sys_domain_path>/</sys_domain_path>
            <sys_id>706d9dbedbc21010b0235c7a489619f1</sys_id>
            <sys_mod_count>2</sys_mod_count>
            <sys_updated_by>admin</sys_updated_by>
            <sys_updated_on>2020-07-20 13:06:49</sys_updated_on>
            <value>6. Not Provided by any Authoritative Source</value>
        </sys_choice>
    </sys_choice>
</record_update>
